pip_services4_azure/__init__.py
pip_services4_azure/clients/AzureFunctionClient.py
pip_services4_azure/clients/CommandableAzureFunctionClient.py
pip_services4_azure/clients/__init__.py
pip_services4_azure/connect/AzureConnectionParams.py
pip_services4_azure/connect/AzureConnectionResolver.py
pip_services4_azure/connect/__init__.py
pip_services4_azure/containers/AzureFunction.py
pip_services4_azure/containers/AzureFunctionContextHelper.py
pip_services4_azure/containers/CommandableAzureFunction.py
pip_services4_azure/containers/__init__.py
pip_services4_azure/services/AzureFunctionAction.py
pip_services4_azure/services/AzureFunctionController.py
pip_services4_azure/services/CommandableAzureFunctionController.py
pip_services4_azure/services/IAzureFunctionController.py
pip_services4_azure/services/__init__.py
pip_services4_azure-0.0.1.dist-info/METADATA
pip_services4_azure-0.0.1.dist-info/WHEEL
pip_services4_azure-0.0.1.dist-info/top_level.txt
pip_services4_azure-0.0.1.dist-info/zip-safe
pip_services4_azure-0.0.1.dist-info/RECORD
